marc2excel
