Metadata-Version: 1.1
Name: marc2excel
Version: 1.2.0
Summary: Convert MARC files to Excel spreadsheets and vice-versa.
Home-page: https://github.com/alexandermendes/marc2excel
Author: Alexander Mendes
Author-email: alexanderhmendes@gmail.com
License: BSD
Platform: UNKNOWN
Classifier: Development Status :: 5 - Production/Stable
Classifier: Intended Audience :: Developers
Classifier: License :: OSI Approved :: BSD License
Classifier: Programming Language :: Python
